Metadata-Version: 2.1
Name: letterpackage
Version: 0.0.1
Summary: Paquete DATA SCIENCE FEB23 EDEM
Author: Alumnos DATA SCIENCE FEB23 EDEM
License: MIT
License-File: LICENSE
